django_gsuite_email/__init__.py
django_gsuite_email/apps.py
django_gsuite_email/backends.py
django_gsuite_email/tests.py
django_gsuite_email/utils.py
django_gsuite_email-0.1.2.dist-info/LICENSE
django_gsuite_email-0.1.2.dist-info/METADATA
django_gsuite_email-0.1.2.dist-info/WHEEL
django_gsuite_email-0.1.2.dist-info/top_level.txt
django_gsuite_email-0.1.2.dist-info/RECORD
